{
  "id": "doc_00036",
  "title": "CodeForge v. Open Runtime Labs \u2014 Summary Judgment Motion",
  "date": "2014-09-14",
  "source": "Court Filing Summary",
  "cluster": "Copyright and Platform Dispute",
  "case_name": "CodeForge v. Open Runtime Labs",
  "court": "U.S. District Court for the Northern District of California",
  "court_type": "district",
  "event_type": "summary_judgment",
  "summary": "Vector Stack moved for summary judgment on a record centered on software interoperability.",
  "entities": [
    "CodeForge v. Open Runtime Labs",
    "Court of Appeals",
    "Developer Ecosystem",
    "Judge Lena Brooks",
    "Open Runtime Labs",
    "Summary Judgment",
    "Supreme Court",
    "U.S. Copyright Office",
    "U.S. District Court for the Northern District of California",
    "Vector Stack",
    "software interoperability"
  ],
  "relationships": [
    {
      "source": "Vector Stack",
      "type": "moved_for_summary_judgment_in",
      "target": "CodeForge v. Open Runtime Labs"
    },
    {
      "source": "Judge Lena Brooks",
      "type": "considering",
      "target": "Summary Judgment"
    },
    {
      "source": "CodeForge v. Open Runtime Labs",
      "type": "filed_in",
      "target": "U.S. District Court for the Northern District of California"
    },
    {
      "source": "CodeForge v. Open Runtime Labs",
      "type": "belongs_to_cluster",
      "target": "Copyright and Platform Dispute"
    },
    {
      "source": "Judge Lena Brooks",
      "type": "assigned_to",
      "target": "CodeForge v. Open Runtime Labs"
    },
    {
      "source": "CodeForge v. Open Runtime Labs",
      "type": "references_topic",
      "target": "software interoperability"
    }
  ],
  "tags": [
    "copyright_and_platform_dispute",
    "summary_judgment",
    "software_interoperability",
    "synthetic",
    "legal",
    "opensight-demo"
  ],
  "analysis_hints": {
    "sentiment": "adverse",
    "importance": 2,
    "timeline_bucket": 2014
  }
}