{
  "id": "doc_03620",
  "title": "United States v. Meridian BioLabs \u2014 Regulatory Notice",
  "date": "2021-05-17",
  "source": "Court Filing Summary",
  "cluster": "Corporate Fraud Trial",
  "case_name": "United States v. Meridian BioLabs",
  "court": "U.S. District Court for the Southern District of New York",
  "court_type": "district",
  "event_type": "regulatory_notice",
  "summary": "U.S. Department of Justice issued a notice connected to allegations involving investor disclosures.",
  "entities": [
    "Court of Appeals",
    "Investor Group",
    "Judge Daniel Pike",
    "Regulatory Notice",
    "Sterling Diagnostics",
    "Supreme Court",
    "U.S. Department of Justice",
    "U.S. District Court for the Southern District of New York",
    "United States",
    "United States v. Meridian BioLabs",
    "investor disclosures"
  ],
  "relationships": [
    {
      "source": "U.S. Department of Justice",
      "type": "issued_notice_involving",
      "target": "Sterling Diagnostics"
    },
    {
      "source": "U.S. Department of Justice",
      "type": "referenced",
      "target": "United States v. Meridian BioLabs"
    },
    {
      "source": "United States v. Meridian BioLabs",
      "type": "filed_in",
      "target": "U.S. District Court for the Southern District of New York"
    },
    {
      "source": "United States v. Meridian BioLabs",
      "type": "belongs_to_cluster",
      "target": "Corporate Fraud Trial"
    },
    {
      "source": "Judge Daniel Pike",
      "type": "assigned_to",
      "target": "United States v. Meridian BioLabs"
    },
    {
      "source": "U.S. Department of Justice",
      "type": "involved_in",
      "target": "United States v. Meridian BioLabs"
    }
  ],
  "tags": [
    "corporate_fraud_trial",
    "regulatory_notice",
    "investor_disclosures",
    "synthetic",
    "legal",
    "opensight-demo"
  ],
  "analysis_hints": {
    "sentiment": "adverse",
    "importance": 2,
    "timeline_bucket": 2021
  }
}